[
  {
    "id": 1,
    "question": "The founder of the Social Democratic Party was ______.",
    "answer": "Ferdinand Lassalle"
  },
  {
    "id": 2,
    "question": "The Nazi Party’s propaganda was led by ______.",
    "answer": "Joseph Goebbels"
  },
  {
    "id": 3,
    "question": "The Vietnam Nationalist Party was formed in ______.",
    "answer": "1927"
  },
  {
    "id": 4,
    "question": "The Secret State Police in Nazi Germany was known as ______.",
    "answer": "Gestapo"
  },
  {
    "id": 5,
    "question": "The Union of South Africa came into being in May ______.",
    "answer": "1910"
  },
  {
    "id": 6,
    "question": "The ANC leader Nelson Mandela was put behind the bars for ______ years.",
    "answer": "27"
  },
  {
    "id": 7,
    "question": "Boers were also known as ______.",
    "answer": "Afrikaners"
  }
]
